plover_palantype/__init__.py
plover_palantype/machine.py
plover_palantype/system.py
plover_palantype-0.7.0.dist-info/DESCRIPTION.rst
plover_palantype-0.7.0.dist-info/METADATA
plover_palantype-0.7.0.dist-info/RECORD
plover_palantype-0.7.0.dist-info/WHEEL
plover_palantype-0.7.0.dist-info/entry_points.txt
plover_palantype-0.7.0.dist-info/metadata.json
plover_palantype-0.7.0.dist-info/top_level.txt
plover_palantype-0.7.0.dist-info/zip-safe
